<?xml version="1.0" encoding="UTF-8" ?>
<!DOCTYPE mapper PUBLIC "-//mybatis.org//DTD Mapper 3.0//EN" "http://mybatis.org/dtd/mybatis-3-mapper.dtd">
<mapper namespace="com.chd.hrp.ass.dao.contract.AssContractMainMapper">
	
	<resultMap id="assContractMain" type="com.chd.hrp.ass.entity.contract.AssContractMain">
	<result property="group_id" column="group_id"/>
	<result property="hos_id" column="hos_id"/>
	<result property="copy_code" column="copy_code"/>
	<result property="contract_id" column="contract_id"/>
	<result property="contract_no" column="contract_no"/>
	<result property="contract_type" column="contract_type"/>
	<result property="contract_ori_no" column="contract_ori_no"/>
	<result property="contract_name" column="contract_name"/>
	<result property="ass_year" column="ass_year"/>
	<result property="ass_month" column="ass_month"/>
	<result property="ven_id" column="ven_id"/>
	<result property="ven_no" column="ven_no"/>
	<result property="sign_date" column="sign_date"/>
	<result property="buy_type" column="buy_type"/>
	<result property="start_date" column="start_date"/>
	<result property="end_date" column="end_date"/>
	<result property="contract_detail" column="contract_detail"/>
	<result property="service_detail" column="service_detail"/>
	<result property="emp_main" column="emp_main"/>
	<result property="provider" column="provider"/>
	<result property="is_bid" column="is_bid"/>
	<result property="contract_money" column="contract_money"/>
	<result property="create_emp" column="create_emp"/>
	<result property="create_date" column="create_date"/>
	<result property="check_emp" column="check_emp"/>
	<result property="check_date" column="check_date"/>
	<result property="state" column="state"/>
	<result property="is_group" column="is_group"/>
	<result property="ven_code" column="ven_code"/>
	<result property="ven_name" column="ven_name"/>
	<result property="emp_main_name" column="emp_main_name"/>
	<result property="create_emp_name" column="create_emp_name"/>
	<result property="check_emp_name" column="check_emp_name"/>
	<result property="cur_code" column="cur_code"/>
	<result property="cur_name" column="cur_name"/>
	</resultMap>
	
	<select id="queryAssContractMainSequence" resultType="java.lang.Long">
		select ASS_CONTRACT_MAIN_SEQ.currval val from dual
	</select>
	
	<insert id="addAssContractMain" useGeneratedKeys="true" >
	
		INSERT INTO ASS_CONTRACT_MAIN (
		<trim suffix="" suffixOverrides=",">
		<if test="group_id != null and group_id != ''">
		group_id
		,
		</if>
		<if test="hos_id != null and hos_id != ''">
		hos_id
		,
		</if>
		<if test="copy_code != null and copy_code != ''">
		copy_code
		,
		</if>
		contract_id
		,
		<if test="contract_no != null and contract_no != ''">
		contract_no
		,
		</if>
		<if test="contract_type != null and contract_type != ''">
		contract_type
		,
		</if>
		<if test="contract_ori_no != null and contract_ori_no != ''">
		contract_ori_no
		,
		</if>
		<if test="contract_name != null and contract_name != ''">
		contract_name
		,
		</if>
		<if test="ass_year != null and ass_year != ''">
		ass_year
		,
		</if>
		<if test="ass_month != null and ass_month != ''">
		ass_month
		,
		</if>
		<if test="ven_id != null and ven_id != ''">
		ven_id
		,
		</if>
		<if test="ven_no != null and ven_no != ''">
		ven_no
		,
		</if>
		<if test="sign_date != null and sign_date != ''">
		sign_date
		,
		</if>
		<if test="buy_type != null and buy_type != ''">
		buy_type
		,
		</if>
		<if test="start_date != null and start_date != ''">
		start_date
		,
		</if>
		<if test="end_date != null and end_date != ''">
		end_date
		,
		</if>
		<if test="contract_detail != null and contract_detail != ''">
		contract_detail
		,
		</if>
		<if test="service_detail != null and service_detail != ''">
		service_detail
		,
		</if>
		<if test="emp_main != null and emp_main != ''">
		emp_main
		,
		</if>
		<if test="provider != null and provider != ''">
		provider
		,
		</if>
		<if test="is_bid != null and is_bid != ''">
		is_bid
		,
		</if>
		<if test="contract_money != null and contract_money != ''">
		contract_money
		,
		</if>
		<if test="create_emp != null and create_emp != ''">
		create_emp
		,
		</if>
		<if test="create_date != null and create_date != ''">
		create_date
		,
		</if>
		<if test="check_emp != null and check_emp != ''">
		check_emp
		,
		</if>
		<if test="check_date != null and check_date != ''">
		check_date
		,
		</if>
		<if test="state != null and state != ''">
		state
		,
		</if>
		<if test="is_group != null and is_group != ''">
		is_group
		,
		</if>
		<if test="cur_code != null and cur_code != ''">
		cur_code
		,
		</if>
		<if test="is_init != null and is_init != ''">
		is_init
		,
		</if>
		</trim>
		) VALUES (
		<trim suffix="" suffixOverrides=",">
		<if test="group_id != null and group_id != ''">
		#{group_id,jdbcType=INTEGER}
		,
		</if>
		<if test="hos_id != null and hos_id != ''">
		#{hos_id,jdbcType=INTEGER}
		,
		</if>
		<if test="copy_code != null and copy_code != ''">
		#{copy_code,jdbcType=VARCHAR}
		,
		</if>
		ASS_CONTRACT_MAIN_SEQ.nextval
		,
		<if test="contract_no != null and contract_no != ''">
		#{contract_no,jdbcType=VARCHAR}
		,
		</if>
		<if test="contract_type != null and contract_type != ''">
		#{contract_type,jdbcType=VARCHAR}
		,
		</if>
		<if test="contract_ori_no != null and contract_ori_no != ''">
		#{contract_ori_no,jdbcType=VARCHAR}
		,
		</if>
		<if test="contract_name != null and contract_name != ''">
		#{contract_name,jdbcType=VARCHAR}
		,
		</if>
		<if test="ass_year != null and ass_year != ''">
		#{ass_year,jdbcType=VARCHAR}
		,
		</if>
		<if test="ass_month != null and ass_month != ''">
		#{ass_month,jdbcType=VARCHAR}
		,
		</if>
		<if test="ven_id != null and ven_id != ''">
		#{ven_id,jdbcType=INTEGER}
		,
		</if>
		<if test="ven_no != null and ven_no != ''">
		#{ven_no,jdbcType=INTEGER}
		,
		</if>
		<if test="sign_date != null and sign_date != ''">
		#{sign_date,jdbcType=DATE}
		,
		</if>
		<if test="buy_type != null and buy_type != ''">
		#{buy_type,jdbcType=VARCHAR}
		,
		</if>
		<if test="start_date != null and start_date != ''">
		#{start_date,jdbcType=DATE}
		,
		</if>
		<if test="end_date != null and end_date != ''">
		#{end_date,jdbcType=DATE}
		,
		</if>
		<if test="contract_detail != null and contract_detail != ''">
		#{contract_detail,jdbcType=VARCHAR}
		,
		</if>
		<if test="service_detail != null and service_detail != ''">
		#{service_detail,jdbcType=VARCHAR}
		,
		</if>
		<if test="emp_main != null and emp_main != ''">
		#{emp_main,jdbcType=INTEGER}
		,
		</if>
		<if test="provider != null and provider != ''">
		#{provider,jdbcType=VARCHAR}
		,
		</if>
		<if test="is_bid != null and is_bid != ''">
		#{is_bid,jdbcType=INTEGER}
		,
		</if>
		<if test="contract_money != null and contract_money != ''">
		#{contract_money,jdbcType=INTEGER}
		,
		</if>
		<if test="create_emp != null and create_emp != ''">
		#{create_emp,jdbcType=INTEGER}
		,
		</if>
		<if test="create_date != null and create_date != ''">
		#{create_date,jdbcType=DATE}
		,
		</if>
		<if test="check_emp != null and check_emp != ''">
		#{check_emp,jdbcType=INTEGER}
		,
		</if>
		<if test="check_date != null and check_date != ''">
		#{check_date,jdbcType=DATE}
		,
		</if>
		<if test="state != null and state != ''">
		#{state,jdbcType=INTEGER}
		,
		</if>
		<if test="is_group != null and is_group != ''">
		#{is_group,jdbcType=INTEGER}
		,
		</if>
		<if test="cur_code != null and cur_code != ''">
		#{cur_code,jdbcType=VARCHAR}
		,
		</if>
		<if test="is_init != null and is_init != ''">
		#{is_init,jdbcType=VARCHAR}
		,
		</if>
		</trim>		
		)
	
	</insert>
	<insert id="addBatchAssContractMain" parameterType="java.util.List" >
	
		INSERT INTO ASS_CONTRACT_MAIN (
		<trim suffix="" suffixOverrides=",">
		<if test="group_id != null and group_id != ''">
		group_id
		,
		</if>
		<if test="hos_id != null and hos_id != ''">
		hos_id
		,
		</if>
		<if test="copy_code != null and copy_code != ''">
		copy_code
		,
		</if>
		<if test="contract_id != null and contract_id != ''">
		contract_id
		,
		</if>
		<if test="contract_no != null and contract_no != ''">
		contract_no
		,
		</if>
		<if test="contract_type != null and contract_type != ''">
		contract_type
		,
		</if>
		<if test="contract_ori_no != null and contract_ori_no != ''">
		contract_ori_no
		,
		</if>
		<if test="contract_name != null and contract_name != ''">
		contract_name
		,
		</if>
		<if test="ass_year != null and ass_year != ''">
		ass_year
		,
		</if>
		<if test="ass_month != null and ass_month != ''">
		ass_month
		,
		</if>
		<if test="ven_id != null and ven_id != ''">
		ven_id
		,
		</if>
		<if test="ven_no != null and ven_no != ''">
		ven_no
		,
		</if>
		<if test="sign_date != null and sign_date != ''">
		sign_date
		,
		</if>
		<if test="buy_type != null and buy_type != ''">
		buy_type
		,
		</if>
		<if test="start_date != null and start_date != ''">
		start_date
		,
		</if>
		<if test="end_date != null and end_date != ''">
		end_date
		,
		</if>
		<if test="contract_detail != null and contract_detail != ''">
		contract_detail
		,
		</if>
		<if test="service_detail != null and service_detail != ''">
		service_detail
		,
		</if>
		<if test="emp_main != null and emp_main != ''">
		emp_main
		,
		</if>
		<if test="provider != null and provider != ''">
		provider
		,
		</if>
		<if test="is_bid != null and is_bid != ''">
		is_bid
		,
		</if>
		<if test="contract_money != null and contract_money != ''">
		contract_money
		,
		</if>
		<if test="create_emp != null and create_emp != ''">
		create_emp
		,
		</if>
		<if test="create_date != null and create_date != ''">
		create_date
		,
		</if>
		<if test="check_emp != null and check_emp != ''">
		check_emp
		,
		</if>
		<if test="check_date != null and check_date != ''">
		check_date
		,
		</if>
		<if test="state != null and state != ''">
		state
		,
		</if>
		<if test="is_group != null and is_group != ''">
		is_group
		,
		</if>
		<if test="cur_code != null and cur_code != ''">
		cur_code
		,
		</if>
		<if test="is_init != null and is_init != ''">
		is_init
		,
		</if>
		</trim>
		) select ASS_CONTRACT_MAIN_SEQ.nextval , t.* from(
		<foreach collection="list" item="item" index="index" separator=" union all " >
			select 		
			<trim suffix="" suffixOverrides=",">
			<if test="group_id != null and group_id != ''">
			#{item.group_id,jdbcType=INTEGER}
			,
			</if>
			<if test="hos_id != null and hos_id != ''">
			#{item.hos_id,jdbcType=INTEGER}
			,
			</if>
			<if test="copy_code != null and copy_code != ''">
			#{item.copy_code,jdbcType=VARCHAR}
			,
			</if>
			<if test="contract_id != null and contract_id != ''">
			#{item.contract_id,jdbcType=INTEGER}
			,
			</if>
			<if test="contract_no != null and contract_no != ''">
			#{item.contract_no,jdbcType=VARCHAR}
			,
			</if>
			<if test="contract_type != null and contract_type != ''">
			#{item.contract_type,jdbcType=VARCHAR}
			,
			</if>
			<if test="contract_ori_no != null and contract_ori_no != ''">
			#{item.contract_ori_no,jdbcType=VARCHAR}
			,
			</if>
			<if test="contract_name != null and contract_name != ''">
			#{item.contract_name,jdbcType=VARCHAR}
			,
			</if>
			<if test="ass_year != null and ass_year != ''">
			#{item.ass_year,jdbcType=VARCHAR}
			,
			</if>
			<if test="ass_month != null and ass_month != ''">
			#{item.ass_month,jdbcType=VARCHAR}
			,
			</if>
			<if test="ven_id != null and ven_id != ''">
			#{item.ven_id,jdbcType=INTEGER}
			,
			</if>
			<if test="ven_no != null and ven_no != ''">
			#{item.ven_no,jdbcType=INTEGER}
			,
			</if>
			<if test="sign_date != null and sign_date != ''">
			#{item.sign_date,jdbcType=DATE}
			,
			</if>
			<if test="buy_type != null and buy_type != ''">
			#{item.buy_type,jdbcType=VARCHAR}
			,
			</if>
			<if test="start_date != null and start_date != ''">
			#{item.start_date,jdbcType=DATE}
			,
			</if>
			<if test="end_date != null and end_date != ''">
			#{item.end_date,jdbcType=DATE}
			,
			</if>
			<if test="contract_detail != null and contract_detail != ''">
			#{item.contract_detail,jdbcType=VARCHAR}
			,
			</if>
			<if test="service_detail != null and service_detail != ''">
			#{item.service_detail,jdbcType=VARCHAR}
			,
			</if>
			<if test="emp_main != null and emp_main != ''">
			#{item.emp_main,jdbcType=INTEGER}
			,
			</if>
			<if test="provider != null and provider != ''">
			#{item.provider,jdbcType=VARCHAR}
			,
			</if>
			<if test="is_bid != null and is_bid != ''">
			#{item.is_bid,jdbcType=INTEGER}
			,
			</if>
			<if test="contract_money != null and contract_money != ''">
			#{item.contract_money,jdbcType=INTEGER}
			,
			</if>
			<if test="create_emp != null and create_emp != ''">
			#{item.create_emp,jdbcType=INTEGER}
			,
			</if>
			<if test="create_date != null and create_date != ''">
			#{item.create_date,jdbcType=DATE}
			,
			</if>
			<if test="check_emp != null and check_emp != ''">
			#{item.check_emp,jdbcType=INTEGER}
			,
			</if>
			<if test="check_date != null and check_date != ''">
			#{item.check_date,jdbcType=DATE}
			,
			</if>
			<if test="state != null and state != ''">
			#{item.state,jdbcType=INTEGER}
			,
			</if>
			<if test="is_group != null and is_group != ''">
			#{item.is_group,jdbcType=INTEGER}
			,
			</if>
			<if test="cur_code != null and cur_code != ''">
			#{item.cur_code,jdbcType=VARCHAR}
			,
			</if>
			<if test="is_init != null and is_init != ''">
			#{item.is_init,jdbcType=INTEGER}
			,
			</if>
			</trim>
		    from dual
		</foreach>
		
	</insert>
	
	
	<update id="updateToExamine" parameterType="java.util.List">
		<foreach collection="list" item="item" index="index" open="begin" close=";end;" separator=";" >
			UPDATE ass_contract_main set state = 1,check_emp = #{item.check_emp},check_date = #{item.check_date} 
			where
			 group_id = #{item.group_id,jdbcType=INTEGER}
			 AND hos_id = #{item.hos_id,jdbcType=INTEGER}
			 AND copy_code = #{item.copy_code,jdbcType=VARCHAR}
			 AND contract_id = #{item.contract_id,jdbcType=INTEGER}
		</foreach>
	</update>
	
	<update id="updateNotToExamine" parameterType="java.util.List">
		<foreach collection="list" item="item" index="index" open="begin" close=";end;" separator=";" >
			UPDATE ass_contract_main set state = 0 ,check_emp = null,check_date = null
		where 
			group_id = #{item.group_id,jdbcType=INTEGER}
			AND hos_id = #{item.hos_id,jdbcType=INTEGER}
			AND copy_code = #{item.copy_code,jdbcType=VARCHAR}
			AND contract_id = #{item.contract_id,jdbcType=INTEGER}
		</foreach>
	</update>
	
	
	
	<update id="updateToFile" parameterType="java.util.List">
		<foreach collection="list" item="item" index="index" open="begin" close=";end;" separator=";" >
		UPDATE ass_contract_main set state = 3
		where
		 group_id = #{item.group_id,jdbcType=INTEGER}
		AND hos_id = #{item.hos_id,jdbcType=INTEGER}
		AND copy_code = #{item.copy_code,jdbcType=VARCHAR}
		AND contract_id = #{item.contract_id,jdbcType=INTEGER}
		</foreach>
	</update>
	
	<update id="updateNotToFile" parameterType="java.util.List">
	<foreach collection="list" item="item" index="index" open="begin" close=";end;" separator=";" >
		UPDATE ass_contract_main set state = 2
		where 
		group_id = #{item.group_id,jdbcType=INTEGER}
		AND hos_id = #{item.hos_id,jdbcType=INTEGER}
		AND copy_code = #{item.copy_code,jdbcType=VARCHAR}
		AND contract_id = #{item.contract_id,jdbcType=INTEGER}
		</foreach>
	</update>
	
	
	<update id="updateToPerform" parameterType="java.util.List">
	<foreach collection="list" item="item" index="index" open="begin" close=";end;" separator=";" >
		UPDATE ass_contract_main set state = 2
		where
		 group_id = #{item.group_id,jdbcType=INTEGER}
		AND hos_id = #{item.hos_id,jdbcType=INTEGER}
		AND copy_code = #{item.copy_code,jdbcType=VARCHAR}
		AND contract_id = #{item.contract_id,jdbcType=INTEGER}
		</foreach>
	</update>
	
	<update id="updateNotToPerform" parameterType="java.util.List">
	<foreach collection="list" item="item" index="index" open="begin" close=";end;" separator=";" >
		UPDATE ass_contract_main set state = 1
		where 
		group_id = #{item.group_id,jdbcType=INTEGER}
		AND hos_id = #{item.hos_id,jdbcType=INTEGER}
		AND copy_code = #{item.copy_code,jdbcType=VARCHAR}
		AND contract_id = #{item.contract_id,jdbcType=INTEGER}
		</foreach>
	</update>
	
	
	
	
	<update id="updateAssContractMain" parameterType="java.util.Map">
	
		UPDATE ass_contract_main 
		<trim prefix="SET"  suffixOverrides=","> 
		<if test="contract_no != null and contract_no != ''">
		contract_no = #{contract_no,jdbcType=VARCHAR}
		,
		</if>
		<if test="contract_type != null and contract_type != ''">
		contract_type = #{contract_type,jdbcType=VARCHAR}
		,
		</if>
		<if test="contract_ori_no != null and contract_ori_no != ''">
		contract_ori_no = #{contract_ori_no,jdbcType=VARCHAR}
		,
		</if>
		<if test="contract_name != null and contract_name != ''">
		contract_name = #{contract_name,jdbcType=VARCHAR}
		,
		</if>
		<if test="ass_year != null and ass_year != ''">
		ass_year = #{ass_year,jdbcType=VARCHAR}
		,
		</if>
		<if test="ass_month != null and ass_month != ''">
		ass_month = #{ass_month,jdbcType=VARCHAR}
		,
		</if>
		<if test="ven_id != null and ven_id != ''">
		ven_id = #{ven_id,jdbcType=INTEGER}
		,
		</if>
		<if test="ven_no != null and ven_no != ''">
		ven_no = #{ven_no,jdbcType=INTEGER}
		,
		</if>
		<if test="sign_date != null and sign_date != ''">
		sign_date = #{sign_date,jdbcType=DATE}
		,
		</if>
		<if test="buy_type != null and buy_type != ''">
		buy_type = #{buy_type,jdbcType=VARCHAR}
		,
		</if>
		<if test="start_date != null and start_date != ''">
		start_date = #{start_date,jdbcType=DATE}
		,
		</if>
		<if test="end_date != null and end_date != ''">
		end_date = #{end_date,jdbcType=DATE}
		,
		</if>
		<if test="contract_detail != null and contract_detail != ''">
		contract_detail = #{contract_detail,jdbcType=VARCHAR}
		,
		</if>
		<if test="service_detail != null and service_detail != ''">
		service_detail = #{service_detail,jdbcType=VARCHAR}
		,
		</if>
		<if test="emp_main != null and emp_main != ''">
		emp_main = #{emp_main,jdbcType=INTEGER}
		,
		</if>
		<if test="provider != null and provider != ''">
		provider = #{provider,jdbcType=VARCHAR}
		,
		</if>
		<if test="is_bid != null and is_bid != ''">
		is_bid = #{is_bid,jdbcType=INTEGER}
		,
		</if>
		<if test="contract_money != null and contract_money != ''">
		contract_money = #{contract_money,jdbcType=INTEGER}
		,
		</if>
		<if test="create_emp != null and create_emp != ''">
		create_emp = #{create_emp,jdbcType=INTEGER}
		,
		</if>
		<if test="create_date != null and create_date != ''">
		create_date = #{create_date,jdbcType=DATE}
		,
		</if>
		<if test="check_emp != null and check_emp != ''">
		check_emp = #{check_emp,jdbcType=INTEGER}
		,
		</if>
		<if test="check_date != null and check_date != ''">
		check_date = #{check_date,jdbcType=DATE}
		,
		</if>
		<if test="state != null and state != ''">
		state = #{state,jdbcType=INTEGER}
		,
		</if>
		<if test="cur_code != null and cur_code != ''">
		cur_code = #{cur_code,jdbcType=VARCHAR}
		,
		</if>
		<if test="is_group != null and is_group != ''">
		is_group = #{is_group,jdbcType=INTEGER}
		</if>
		</trim>
		
		<where>    
		<if test="group_id != null and group_id != ''">
		AND group_id =#{group_id,jdbcType=INTEGER}
		</if>
		<if test="hos_id != null and hos_id != ''">
		AND hos_id =#{hos_id,jdbcType=INTEGER}
		</if>
		<if test="copy_code != null and copy_code != ''">
		AND copy_code =#{copy_code,jdbcType=VARCHAR}
		</if>
		<if test="contract_id != null and contract_id != ''">
		AND contract_id =#{contract_id,jdbcType=INTEGER}
		</if>
		
	</where> 
	</update>
	<update id="updateBatchAssContractMain" parameterType="java.util.List">
	
		<foreach collection="list" item="item" index="index" open="begin" close=";end;" separator=";" >
			UPDATE ass_contract_main 
			<trim prefix="SET"  suffixOverrides=","> 
			<if test="contract_no != null and contract_no != ''">
			contract_no = #{item.contract_no,jdbcType=VARCHAR}
			,
			</if>
			<if test="contract_type != null and contract_type != ''">
			contract_type = #{item.contract_type,jdbcType=VARCHAR}
			,
			</if>
			<if test="contract_ori_no != null and contract_ori_no != ''">
			contract_ori_no = #{item.contract_ori_no,jdbcType=VARCHAR}
			,
			</if>
			<if test="contract_name != null and contract_name != ''">
			contract_name = #{item.contract_name,jdbcType=VARCHAR}
			,
			</if>
			<if test="ass_year != null and ass_year != ''">
			ass_year = #{item.ass_year,jdbcType=VARCHAR}
			,
			</if>
			<if test="ass_month != null and ass_month != ''">
			ass_month = #{item.ass_month,jdbcType=VARCHAR}
			,
			</if>
			<if test="ven_id != null and ven_id != ''">
			ven_id = #{item.ven_id,jdbcType=INTEGER}
			,
			</if>
			<if test="ven_no != null and ven_no != ''">
			ven_no = #{item.ven_no,jdbcType=INTEGER}
			,
			</if>
			<if test="sign_date != null and sign_date != ''">
			sign_date = #{item.sign_date,jdbcType=DATE}
			,
			</if>
			<if test="buy_type != null and buy_type != ''">
			buy_type = #{item.buy_type,jdbcType=VARCHAR}
			,
			</if>
			<if test="start_date != null and start_date != ''">
			start_date = #{item.start_date,jdbcType=DATE}
			,
			</if>
			<if test="end_date != null and end_date != ''">
			end_date = #{item.end_date,jdbcType=DATE}
			,
			</if>
			<if test="contract_detail != null and contract_detail != ''">
			contract_detail = #{item.contract_detail,jdbcType=VARCHAR}
			,
			</if>
			<if test="service_detail != null and service_detail != ''">
			service_detail = #{item.service_detail,jdbcType=VARCHAR}
			,
			</if>
			<if test="emp_main != null and emp_main != ''">
			emp_main = #{item.emp_main,jdbcType=INTEGER}
			,
			</if>
			<if test="provider != null and provider != ''">
			provider = #{item.provider,jdbcType=VARCHAR}
			,
			</if>
			<if test="is_bid != null and is_bid != ''">
			is_bid = #{item.is_bid,jdbcType=INTEGER}
			,
			</if>
			<if test="contract_money != null and contract_money != ''">
			contract_money = #{item.contract_money,jdbcType=INTEGER}
			,
			</if>
			<if test="create_emp != null and create_emp != ''">
			create_emp = #{item.create_emp,jdbcType=INTEGER}
			,
			</if>
			<if test="create_date != null and create_date != ''">
			create_date = #{item.create_date,jdbcType=DATE}
			,
			</if>
			<if test="check_emp != null and check_emp != ''">
			check_emp = #{item.check_emp,jdbcType=INTEGER}
			,
			</if>
			<if test="check_date != null and check_date != ''">
			check_date = #{item.check_date,jdbcType=DATE}
			,
			</if>
			<if test="state != null and state != ''">
			state = #{item.state,jdbcType=INTEGER}
			,
			</if>
			<if test="cur_code != null and cur_code != ''">
			cur_code = #{item.cur_code,jdbcType=VARCHAR}
			,
			</if>
			<if test="is_group != null and is_group != ''">
			is_group = #{item.is_group,jdbcType=INTEGER}
			,
			</if>
			</trim>
			<where>                     
			<if test="group_id != null and group_id != ''">
			AND group_id = #{group_id,jdbcType=INTEGER}
			</if>  
			<if test="hos_id != null and hos_id != ''">
			AND hos_id = #{hos_id,jdbcType=INTEGER}
			</if>  
			<if test="copy_code != null and copy_code != ''">
			AND copy_code = #{copy_code,jdbcType=VARCHAR}
			</if>  
			<if test="contract_id != null and contract_id != ''">
			AND contract_id = #{contract_id,jdbcType=INTEGER}
			</if>  
			<if test="contract_no != null and contract_no != ''">
			AND contract_no = #{contract_no,jdbcType=VARCHAR}
			</if>  
			<if test="contract_type != null and contract_type != ''">
			AND contract_type = #{contract_type,jdbcType=VARCHAR}
			</if>  
			<if test="contract_ori_no != null and contract_ori_no != ''">
			AND contract_ori_no = #{contract_ori_no,jdbcType=VARCHAR}
			</if>  
			<if test="contract_name != null and contract_name != ''">
			AND contract_name = #{contract_name,jdbcType=VARCHAR}
			</if>  
			<if test="ass_year != null and ass_year != ''">
			AND ass_year = #{ass_year,jdbcType=VARCHAR}
			</if>  
			<if test="ass_month != null and ass_month != ''">
			AND ass_month = #{ass_month,jdbcType=VARCHAR}
			</if>  
			<if test="ven_id != null and ven_id != ''">
			AND ven_id = #{ven_id,jdbcType=INTEGER}
			</if>  
			<if test="ven_no != null and ven_no != ''">
			AND ven_no = #{ven_no,jdbcType=INTEGER}
			</if>  
			<if test="sign_date != null and sign_date != ''">
			AND sign_date = #{sign_date,jdbcType=DATE}
			</if>  
			<if test="buy_type != null and buy_type != ''">
			AND buy_type = #{buy_type,jdbcType=VARCHAR}
			</if>  
			<if test="start_date != null and start_date != ''">
			AND start_date = #{start_date,jdbcType=DATE}
			</if>  
			<if test="end_date != null and end_date != ''">
			AND end_date = #{end_date,jdbcType=DATE}
			</if>  
			<if test="contract_detail != null and contract_detail != ''">
			AND contract_detail = #{contract_detail,jdbcType=VARCHAR}
			</if>  
			<if test="service_detail != null and service_detail != ''">
			AND service_detail = #{service_detail,jdbcType=VARCHAR}
			</if>  
			<if test="emp_main != null and emp_main != ''">
			AND emp_main = #{emp_main,jdbcType=INTEGER}
			</if>  
			<if test="provider != null and provider != ''">
			AND provider = #{provider,jdbcType=VARCHAR}
			</if>  
			<if test="is_bid != null and is_bid != ''">
			AND is_bid = #{is_bid,jdbcType=INTEGER}
			</if>  
			<if test="contract_money != null and contract_money != ''">
			AND contract_money = #{contract_money,jdbcType=INTEGER}
			</if>  
			<if test="create_emp != null and create_emp != ''">
			AND create_emp = #{create_emp,jdbcType=INTEGER}
			</if>  
			<if test="create_date != null and create_date != ''">
			AND create_date = #{create_date,jdbcType=DATE}
			</if>  
			<if test="check_emp != null and check_emp != ''">
			AND check_emp = #{check_emp,jdbcType=INTEGER}
			</if>  
			<if test="check_date != null and check_date != ''">
			AND check_date = #{check_date,jdbcType=DATE}
			</if>  
			<if test="state != null and state != ''">
			AND state = #{state,jdbcType=INTEGER}
			</if>  
			<if test="is_group != null and is_group != ''">
			AND is_group = #{is_group,jdbcType=INTEGER}
			</if>  
			</where>  			
		</foreach>
	</update>
	
	<delete id="deleteAssContractMain" parameterType="java.util.Map">
	
		DELETE FROM ass_contract_main 
		<where>                     
		<if test="group_id != null and group_id != ''">
		AND group_id = #{group_id,jdbcType=INTEGER}
		</if>
		<if test="hos_id != null and hos_id != ''">
		AND hos_id = #{hos_id,jdbcType=INTEGER}
		</if>
		<if test="copy_code != null and copy_code != ''">
		AND copy_code = #{copy_code,jdbcType=VARCHAR}
		</if>
		<if test="contract_id != null and contract_id != ''">
		AND contract_id = #{contract_id,jdbcType=INTEGER}
		</if>
		<if test="contract_no != null and contract_no != ''">
		AND contract_no = #{contract_no,jdbcType=VARCHAR}
		</if>
		</where>  
	</delete>
	<delete id="deleteBatchAssContractMain" parameterType="java.util.List">
		DELETE FROM ass_contract_main WHERE
	<foreach collection="list" index="index" item="item" open="(" separator="or" close=")">
				group_id = #{item.group_id,jdbcType=INTEGER}
				 and 
				hos_id = #{item.hos_id,jdbcType=INTEGER}
				 and 
				copy_code = #{item.copy_code,jdbcType=VARCHAR}
				 and 
				contract_id = #{item.contract_id,jdbcType=INTEGER}
				
	</foreach>
	</delete>
	
	
	<select id="queryAssContractMain" parameterType="java.util.Map" resultMap="assContractMain" >
	
		SELECT  
    acm.group_id,
    acm.hos_id,
    acm.copy_code,
    acm.contract_id,
    acm.contract_no,
    acm.contract_type,
    acm.contract_ori_no,
    acm.contract_name,
    acm.ass_year,
    acm.ass_month,
    acm.ven_id,
    acm.ven_no,
    acm.sign_date,
    acm.buy_type,
    acm.start_date,
    acm.end_date,
    acm.contract_detail,
    acm.service_detail,
    acm.emp_main,
    acm.provider,
    acm.is_bid,
    acm.contract_money,
    acm.create_emp,
    acm.create_date,
    acm.check_emp,
    acm.check_date,
    acm.state,
    acm.is_group,
    acm.cur_code,
    hsd.sup_code ven_code,
    hsd.sup_name ven_name,
    su.user_name emp_main_name,
    su1.user_name create_emp_name,
    su2.user_name check_emp_name
    FROM ASS_CONTRACT_MAIN acm
    LEFT JOIN
    (
    select acd.contract_id,acd.group_id,acd.hos_id,acd.copy_code from ass_contract_detail acd
           LEFT JOIN ass_no_dict ad ON acd.ass_id = ad.ass_id
            AND acd.group_id = ad.group_id
            AND acd.hos_id = ad.hos_id
            AND acd.copy_code = ad.copy_code
            AND ad.is_stop = 0 
            LEFT JOIN ass_type_dict atd ON ad.ass_type_id = atd.ass_type_id
            AND ad.group_id = atd.group_id
            AND ad.hos_id = atd.hos_id
            AND ad.copy_code = atd.copy_code 
            where atd.ass_naturs= #{ass_naturs,jdbcType=VARCHAR}
            group by  acd.contract_id,acd.group_id,acd.hos_id,acd.copy_code
    ) det ON
    acm.contract_id = det.contract_id
    AND acm.group_id = det.group_id
    AND acm.hos_id = det.hos_id
    AND acm.copy_code = det.copy_code  
    left join HOS_SUP_DICT hsd on acm.group_id=hsd.group_id and acm.hos_id=hsd.hos_id and acm.ven_id=hsd.sup_id and acm.ven_no=hsd.sup_no
    left join SYS_USER su on acm.group_id=su.group_id and acm.hos_id=su.hos_id and acm.emp_main=su.user_id
    left join Sys_User su1 on acm.group_id=su1.group_id and acm.hos_id=su1.hos_id and acm.create_emp=su1.user_id
    left join Sys_User su2 on acm.group_id=su2.group_id and acm.hos_id=su2.hos_id and acm.check_emp=su2.user_id
		<where>                     
		<if test="group_id != null and group_id != ''">
		AND acm.group_id = #{group_id,jdbcType=INTEGER}
		</if>
		<if test="hos_id != null and hos_id != ''">
		AND acm.hos_id = #{hos_id,jdbcType=INTEGER}
		</if>
		<if test="copy_code != null and copy_code != ''">
		AND acm.copy_code = #{copy_code,jdbcType=VARCHAR}
		</if>
		<if test="contract_id != null and contract_id != ''">
		AND acm.contract_id = #{contract_id,jdbcType=INTEGER}
		</if>
		<if test="contract_no != null and contract_no != ''">
		AND acm.contract_no like '%${contract_no}%'
		</if>
		<if test="contract_type != null and contract_type != ''">
		AND acm.contract_type = #{contract_type,jdbcType=VARCHAR}
		</if>
		<if test="contract_ori_no != null and contract_ori_no != ''">
		AND acm.contract_ori_no like '%${contract_ori_no}%'
		</if>
		<if test="contract_name != null and contract_name != ''">
		AND acm.contract_name like '%${contract_name}%'
		</if>
		<if test="ass_year != null and ass_year != ''">
		AND acm.ass_year = #{ass_year,jdbcType=VARCHAR}
		</if>
		<if test="ass_month1 != null and ass_month1 != '' and ass_month2 != null and ass_month2 != ''">
		AND acm.ass_month between #{ass_month1} and #{ass_month2}
		</if>
		<if test="ven_id != null and ven_id != ''">
		AND acm.ven_id = #{ven_id,jdbcType=INTEGER}
		</if>
		<if test="ven_no != null and ven_no != ''">
		AND acm.ven_no = #{ven_no,jdbcType=INTEGER}
		</if>
		<if test="sign_date1 != null and sign_date1 != '' and sign_date2 != null and sign_date2 != ''">
		AND acm.sign_date between to_date(#{sign_date1},'yyyy/MM/dd') and to_date(#{sign_date2},'yyyy/MM/dd')
		</if>
		<if test="buy_type != null and buy_type != ''">
		AND acm.buy_type = #{buy_type,jdbcType=VARCHAR}
		</if>
		<if test="start_date != null and start_date != ''">
		AND acm.start_date = #{start_date,jdbcType=DATE}
		</if>
		<if test="end_date != null and end_date != ''">
		AND acm.end_date = #{end_date,jdbcType=DATE}
		</if>
		<if test="contract_detail != null and contract_detail != ''">
		AND acm.contract_detail = #{contract_detail,jdbcType=VARCHAR}
		</if>
		<if test="service_detail != null and service_detail != ''">
		AND acm.service_detail = #{service_detail,jdbcType=VARCHAR}
		</if>
		<if test="emp_main != null and emp_main != ''">
		AND acm.emp_main = #{emp_main,jdbcType=INTEGER}
		</if>
		<if test="provider != null and provider != ''">
		AND acm.provider = #{provider,jdbcType=VARCHAR}
		</if>
		<if test="is_bid != null and is_bid != ''">
		AND acm.is_bid = #{is_bid,jdbcType=INTEGER}
		</if>
		<if test="contract_money != null and contract_money != ''">
		AND acm.contract_money = #{contract_money,jdbcType=INTEGER}
		</if>
		<if test="create_emp != null and create_emp != ''">
		AND acm.create_emp = #{create_emp,jdbcType=INTEGER}
		</if>
		<if test="create_date1 != null and create_date1 != '' and create_date2 != null and create_date2 != ''">
		AND acm.create_date between to_date(#{create_date1},'yyyy/MM/dd') and to_date(#{create_date2},'yyyy/MM/dd')
		</if>
		<if test="check_emp != null and check_emp != ''">
		AND acm.check_emp = #{check_emp,jdbcType=INTEGER}
		</if>
		<if test="check_date1 != null and check_date1 != '' and check_date2 != null and check_date2 != ''">
		AND acm.check_date between to_date(#{check_date1},'yyyy/MM/dd') and to_date(#{check_date2},'yyyy/MM/dd')
		</if>
		<if test="state != null and state != ''">
		AND acm.state = #{state,jdbcType=INTEGER}
		</if>
		<if test="is_group != null and is_group != ''">
		AND acm.is_group = #{is_group,jdbcType=INTEGER}
		</if>
		<if test="is_init != null and is_init != ''">
		AND acm.is_init = #{is_init,jdbcType=INTEGER}
		</if>
		<if test="is_exists != null and is_exists != ''">
		AND not exists(select 1 from ass_in_contract_map where group_id = #{group_id} and hos_id = #{hos_id} and copy_code = #{copy_code} and contract_id = acm.contract_id)
		</if>
		<if test="is_hos_exists != null and is_hos_exists != ''">
		AND not exists(select 1 from ASS_CONTRACT_GROUP_HOS where group_id = #{group_id} and hos_id = #{hos_id} and copy_code = #{copy_code} and  HOS_CONTRACT_ID = acm.contract_id)
		</if>
		<if test="isExistsAccept != null and isExistsAccept != ''">
		AND not exists(select 1 from ASS_ACCEPT_CONTRACT_MAP where group_id = #{group_id} and hos_id = #{hos_id} and copy_code = #{copy_code} and  CONTRACT_ID = acm.contract_id)
		</if>
		<if test="isExistsIns != null and isExistsIns != ''">
		AND not exists(select 1 from ASS_INS_CONTRACT_MAP where group_id = #{group_id} and hos_id = #{hos_id} and copy_code = #{copy_code} and  CONTRACT_ID = acm.contract_id)
		</if>
		</where>   
		order by contract_no desc
	</select>
	<select id="queryAssContractMainByCode" resultMap="assContractMain"  parameterType="java.util.Map" >
	
		SELECT 
    acm.group_id,
    acm.hos_id,
    acm.copy_code,
    acm.contract_id,
    acm.contract_no,
    acm.contract_type,
    acm.contract_ori_no,
    acm.contract_name,
    acm.ass_year,
    acm.ass_month,
    acm.ven_id,
    acm.ven_no,
    acm.sign_date,
    acm.buy_type,
    acm.start_date,
    acm.end_date,
    acm.contract_detail,
    acm.service_detail,
    acm.emp_main,
    acm.provider,
    acm.is_bid,
    acm.contract_money,
    acm.create_emp,
    acm.create_date,
    acm.check_emp,
    acm.check_date,
    acm.state,
    acm.is_group,
    acm.cur_code,
    hsd.sup_code ven_code,
    hsd.sup_name ven_name,
    su.user_name emp_main_name,
    su1.user_name create_emp_name,
    su2.user_name check_emp_name
    FROM ASS_CONTRACT_MAIN acm
    left join HOS_SUP_DICT hsd on acm.group_id=hsd.group_id and acm.hos_id=hsd.hos_id and acm.ven_id=hsd.sup_id and acm.ven_no=hsd.sup_no
    left join SYS_USER su on acm.group_id=su.group_id and acm.hos_id=su.hos_id and acm.emp_main=su.user_id
    left join Sys_User su1 on acm.group_id=su1.group_id and acm.hos_id=su1.hos_id and acm.create_emp=su1.user_id
    left join Sys_User su2 on acm.group_id=su2.group_id and acm.hos_id=su2.hos_id and acm.check_emp=su2.user_id
		WHERE 
		acm.group_id = #{group_id,jdbcType=INTEGER}   and 
		acm.hos_id = #{hos_id,jdbcType=INTEGER}   and 
		acm.copy_code = #{copy_code,jdbcType=VARCHAR}   and 
		acm.contract_id = #{contract_id,jdbcType=INTEGER} 
	
	</select>
	<select id="queryAssContractMainByUniqueness" resultMap="assContractMain"  parameterType="java.util.Map" >
	
		SELECT 
		group_id,
		hos_id,
		copy_code,
		contract_id,
		contract_no,
		contract_type,
		contract_ori_no,
		contract_name,
		ass_year,
		ass_month,
		ven_id,
		ven_no,
		sign_date,
		buy_type,
		start_date,
		end_date,
		contract_detail,
		service_detail,
		emp_main,
		provider,
		is_bid,
		contract_money,
		create_emp,
		create_date,
		check_emp,
		check_date,
		state,
		is_group,
		cur_code
		FROM ASS_CONTRACT_MAIN 
		<where>                     
		<if test="group_id != null and group_id != ''">
		AND group_id = #{group_id,jdbcType=INTEGER}
		</if>
		<if test="hos_id != null and hos_id != ''">
		AND hos_id = #{hos_id,jdbcType=INTEGER}
		</if>
		<if test="copy_code != null and copy_code != ''">
		AND copy_code = #{copy_code,jdbcType=VARCHAR}
		</if>
		<if test="contract_id != null and contract_id != ''">
		AND contract_id = #{contract_id,jdbcType=INTEGER}
		</if>
		<if test="contract_no != null and contract_no != ''">
		AND contract_no = #{contract_no,jdbcType=VARCHAR}
		</if>
		<if test="contract_type != null and contract_type != ''">
		AND contract_type = #{contract_type,jdbcType=VARCHAR}
		</if>
		<if test="contract_ori_no != null and contract_ori_no != ''">
		AND contract_ori_no = #{contract_ori_no,jdbcType=VARCHAR}
		</if>
		<if test="contract_name != null and contract_name != ''">
		AND contract_name = #{contract_name,jdbcType=VARCHAR}
		</if>
		<if test="ass_year != null and ass_year != ''">
		AND ass_year = #{ass_year,jdbcType=VARCHAR}
		</if>
		<if test="ass_month != null and ass_month != ''">
		AND ass_month = #{ass_month,jdbcType=VARCHAR}
		</if>
		<if test="ven_id != null and ven_id != ''">
		AND ven_id = #{ven_id,jdbcType=INTEGER}
		</if>
		<if test="ven_no != null and ven_no != ''">
		AND ven_no = #{ven_no,jdbcType=INTEGER}
		</if>
		<if test="sign_date != null and sign_date != ''">
		AND sign_date = #{sign_date,jdbcType=DATE}
		</if>
		<if test="buy_type != null and buy_type != ''">
		AND buy_type = #{buy_type,jdbcType=VARCHAR}
		</if>
		<if test="start_date != null and start_date != ''">
		AND start_date = #{start_date,jdbcType=DATE}
		</if>
		<if test="end_date != null and end_date != ''">
		AND end_date = #{end_date,jdbcType=DATE}
		</if>
		<if test="contract_detail != null and contract_detail != ''">
		AND contract_detail = #{contract_detail,jdbcType=VARCHAR}
		</if>
		<if test="service_detail != null and service_detail != ''">
		AND service_detail = #{service_detail,jdbcType=VARCHAR}
		</if>
		<if test="emp_main != null and emp_main != ''">
		AND emp_main = #{emp_main,jdbcType=INTEGER}
		</if>
		<if test="provider != null and provider != ''">
		AND provider = #{provider,jdbcType=VARCHAR}
		</if>
		<if test="is_bid != null and is_bid != ''">
		AND is_bid = #{is_bid,jdbcType=INTEGER}
		</if>
		<if test="contract_money != null and contract_money != ''">
		AND contract_money = #{contract_money,jdbcType=INTEGER}
		</if>
		<if test="create_emp != null and create_emp != ''">
		AND create_emp = #{create_emp,jdbcType=INTEGER}
		</if>
		<if test="create_date != null and create_date != ''">
		AND create_date = #{create_date,jdbcType=DATE}
		</if>
		<if test="check_emp != null and check_emp != ''">
		AND check_emp = #{check_emp,jdbcType=INTEGER}
		</if>
		<if test="check_date != null and check_date != ''">
		AND check_date = #{check_date,jdbcType=DATE}
		</if>
		<if test="state != null and state != ''">
		AND state = #{state,jdbcType=INTEGER}
		</if>
		<if test="is_group != null and is_group != ''">
		AND is_group = #{is_group,jdbcType=INTEGER}
		</if>
		</where>   
		order by group_id asc
	</select>
	<select id="queryAssContractMainExists" resultMap="assContractMain"  parameterType="java.util.Map" >
	
		SELECT 
		group_id,
		hos_id,
		copy_code,
		contract_id,
		contract_no,
		contract_type,
		contract_ori_no,
		contract_name,
		ass_year,
		ass_month,
		ven_id,
		ven_no,
		sign_date,
		buy_type,
		start_date,
		end_date,
		contract_detail,
		service_detail,
		emp_main,
		provider,
		is_bid,
		contract_money,
		create_emp,
		create_date,
		check_emp,
		check_date,
		state,
		is_group,
		cur_code
		FROM ASS_CONTRACT_MAIN 
		<where>                     
		<if test="group_id != null and group_id != ''">
		AND group_id = #{group_id,jdbcType=INTEGER}
		</if>
		<if test="hos_id != null and hos_id != ''">
		AND hos_id = #{hos_id,jdbcType=INTEGER}
		</if>
		<if test="copy_code != null and copy_code != ''">
		AND copy_code = #{copy_code,jdbcType=VARCHAR}
		</if>
		<if test="contract_id != null and contract_id != ''">
		AND contract_id = #{contract_id,jdbcType=INTEGER}
		</if>
		<if test="contract_no != null and contract_no != ''">
		AND contract_no = #{contract_no,jdbcType=VARCHAR}
		</if>
		<if test="contract_type != null and contract_type != ''">
		AND contract_type = #{contract_type,jdbcType=VARCHAR}
		</if>
		<if test="contract_ori_no != null and contract_ori_no != ''">
		AND contract_ori_no = #{contract_ori_no,jdbcType=VARCHAR}
		</if>
		<if test="contract_name != null and contract_name != ''">
		AND contract_name = #{contract_name,jdbcType=VARCHAR}
		</if>
		<if test="ass_year != null and ass_year != ''">
		AND ass_year = #{ass_year,jdbcType=VARCHAR}
		</if>
		<if test="ass_month != null and ass_month != ''">
		AND ass_month = #{ass_month,jdbcType=VARCHAR}
		</if>
		<if test="ven_id != null and ven_id != ''">
		AND ven_id = #{ven_id,jdbcType=INTEGER}
		</if>
		<if test="ven_no != null and ven_no != ''">
		AND ven_no = #{ven_no,jdbcType=INTEGER}
		</if>
		<if test="sign_date != null and sign_date != ''">
		AND sign_date = #{sign_date,jdbcType=DATE}
		</if>
		<if test="buy_type != null and buy_type != ''">
		AND buy_type = #{buy_type,jdbcType=VARCHAR}
		</if>
		<if test="start_date != null and start_date != ''">
		AND start_date = #{start_date,jdbcType=DATE}
		</if>
		<if test="end_date != null and end_date != ''">
		AND end_date = #{end_date,jdbcType=DATE}
		</if>
		<if test="contract_detail != null and contract_detail != ''">
		AND contract_detail = #{contract_detail,jdbcType=VARCHAR}
		</if>
		<if test="service_detail != null and service_detail != ''">
		AND service_detail = #{service_detail,jdbcType=VARCHAR}
		</if>
		<if test="emp_main != null and emp_main != ''">
		AND emp_main = #{emp_main,jdbcType=INTEGER}
		</if>
		<if test="provider != null and provider != ''">
		AND provider = #{provider,jdbcType=VARCHAR}
		</if>
		<if test="is_bid != null and is_bid != ''">
		AND is_bid = #{is_bid,jdbcType=INTEGER}
		</if>
		<if test="contract_money != null and contract_money != ''">
		AND contract_money = #{contract_money,jdbcType=INTEGER}
		</if>
		<if test="create_emp != null and create_emp != ''">
		AND create_emp = #{create_emp,jdbcType=INTEGER}
		</if>
		<if test="create_date != null and create_date != ''">
		AND create_date = #{create_date,jdbcType=DATE}
		</if>
		<if test="check_emp != null and check_emp != ''">
		AND check_emp = #{check_emp,jdbcType=INTEGER}
		</if>
		<if test="check_date != null and check_date != ''">
		AND check_date = #{check_date,jdbcType=DATE}
		</if>
		<if test="state != null and state != ''">
		AND state = #{state,jdbcType=INTEGER}
		</if>
		<if test="is_group != null and is_group != ''">
		AND is_group = #{is_group,jdbcType=INTEGER}
		</if>
		</where>   
		order by group_id asc
	</select>
</mapper>

