<?xml version="1.0" encoding="gb2312"?>
<root> 
	<menu_node code="12" name="项目成本管理系统"> 
		<menu_node code="business" name="业务功能" accordion="true">
			<menu_node name="作业成本法"> 
				<menu_node name="成本数据维护"> 
					<menu_node name="收入数据采集" 
						url="hrp/htc/task/cost/deptincome/htcTaskDeptIncomeMainPage.do?isCheck=false">
						<perm name="添加" permid="addHtcTaskDeptIncome" />
						<perm name="删除" permid="deleteHtcTaskDeptIncome" />
						<perm name="修改" permid="updateHtcTaskDeptIncome" /> 
						<perm name="查询" permid="queryHtcTaskDeptIncome" />
					</menu_node>
					<menu_node name="成本数据采集"
						url="hrp/htc/task/cost/deptcost/htcTaskDeptCostMainPage.do?isCheck=false">
						<perm name="添加" permid="addHtcTaskDeptCost" />
						<perm name="删除" permid="deleteHtcTaskDeptCost" />
						<perm name="修改" permid="updateHtcTaskDeptCost" />
						<perm name="查询" permid="queryHtcTaskDeptCost" />
					</menu_node>
					<menu_node name="活劳动数据采集">
						<menu_node name="工资数据采集"
							url="hrp/htc/task/deptcost/peoplewagedetail/htcPeopleWageDetailMainPage.do?isCheck=false">
							<perm name="添加" permid="addHtcPeopleWageDetail" />
							<perm name="删除" permid="deleteHtcPeopleWageDetail" />
							<perm name="修改" permid="updateHtcPeopleWageDetailItem" />
							<perm name="查询" permid="queryHtcPeopleWageDetail" />
						</menu_node>
						<menu_node name="奖金数据采集"
							url="hrp/htc/task/deptcost/peoplebonusdetail/htcPeopleBonusDetailMainPage.do?isCheck=false">
							<perm name="添加" permid="addHtcPeopleBonusDetail" />
							<perm name="删除" permid="deleteHtcPeopleBonusDetail" />
							<perm name="修改" permid="updateHtcPeopleBonusDetailItem" />
							<perm name="查询" permid="queryHtcPeopleBonusDetail" />
						</menu_node>
						<menu_node name="活劳动成本归集"
							url="hrp/htc/task/deptcost/peoplecostdetail/htcPeopleCostDetailMainPage.do?isCheck=false">
							<perm name="删除" permid="deleteHtcPeopleCostDetail" />
							<perm name="修改" permid="updateHtcPeopleCostDetail" />
							<perm name="查询" permid="queryHtcPeopleCostDetail" />
							<perm name="采集" permid="collectHtcPeopleCostDetail" />
							<perm name="数据核对" permid="checkHtcPeopleCostDetail" />
						</menu_node>
					</menu_node>
					<menu_node name="物化劳动数据采集">
						<menu_node name="材料支出数据采集"
							url="hrp/htc/task/deptcost/deptmaterialdetail/htcDeptMaterialDetailMainPage.do?isCheck=false">
							<perm name="添加" permid="addHtcDeptMaterialDetail" />
							<perm name="删除" permid="deleteHtcDeptMaterialDetail" />
							<perm name="修改" permid="updateHtcDeptMaterialDetail" />
							<perm name="查询" permid="queryHtcDeptMaterialDetail" />
						</menu_node>
						<menu_node name="材料支出数据归集"
							url="hrp/htc/task/deptcost/deptmaterialdetail/htcDeptMaterialCostDetailMainPage.do?isCheck=false">
							<perm name="查询" permid="queryHtcDeptMaterialCostDetail" />
							<perm name="数据核对" permid="checkHtcDeptMaterialCostDetail" />
						</menu_node>
						<menu_node name="固定资产折旧数据采集"
							url="hrp/htc/task/deptcost/deptfassetdetail/htcDeptFassetDetailMainPage.do?isCheck=false">
							<perm name="添加" permid="addHtcDeptFassetDetail" />
							<perm name="删除" permid="deleteHtcDeptFassetDetail" />
							<perm name="修改" permid="updateHtcDeptFassetDetail" />
							<perm name="查询" permid="queryHtcDeptFassetDetail" />
						</menu_node>
						<menu_node name="固定资产折旧数据归集"
							url="hrp/htc/task/deptcost/deptfassetdetail/htcDeptFassetCostDetailMainPage.do?isCheck=false">
							<perm name="查询" permid="queryHtcDeptFassetCostDetail" />
							<perm name="数据核对" permid="checkHtcDeptFassetCostDetail" />
						</menu_node>
						<menu_node name="无形资产折旧数据采集"
							url="hrp/htc/task/deptcost/deptiassetdetail/htcDeptIassetDetailMainPage.do?isCheck=false">
							<perm name="添加" permid="addHtcDeptIassetDetail" />
							<perm name="删除" permid="deleteHtcDeptIassetDetail" />
							<perm name="修改" permid="updateHtcDeptIassetDetail" />
							<perm name="查询" permid="queryHtcDeptIassetDetail" />
						</menu_node>
						<menu_node name="无形资产折旧数据归集"
							url="hrp/htc/task/deptcost/deptiassetdetail/htcDeptIassetCostDetailMain.do?isCheck=false">
							<perm name="查询" permid="queryHtcDeptIassetCostDetail" />
							<perm name="数据核对" permid="sumHtcDeptIassetCostDetail" />
						</menu_node>
					</menu_node>
				</menu_node>
				<menu_node name="核算方案维护">
					<menu_node name="核算方案维护"
						url="hrp/htc/task/plan/set/htcTaskPlanSetMainPage.do?isCheck=false">
						<perm name="添加" permid="addHtcTaskPlanSet" />
						<perm name="删除" permid="deleteHtcTaskPlanSet" />
						<perm name="修改" permid="updateHtcTaskPlanSet" />
						<perm name="查询" permid="queryHtcTaskPlanSet" />
					</menu_node>
					<menu_node name="科室对应关系设置"
						url="hrp/htc/task/plan/deptrela/htcTaskDeptRelaMainPage.do?isCheck=false">
						<perm name="添加" permid="addHtcTaskDeptRela" />
						<perm name="删除" permid="deleteHtcTaskDeptRela" />
						<perm name="修改" permid="updateHtcTaskDeptRela" />
						<perm name="查询" permid="queryHtcTaskDeptRela" />
					</menu_node>
					<menu_node name="科室资源定义">
						<menu_node name="科室作业定义"
							url="hrp/htc/task/projectcost/deptworkrela/htcDeptWorkRelaMainPage.do?isCheck=false">
							<perm name="添加" permid="addHtcDeptWorkRela" />
							<perm name="删除" permid="deleteHtcDeptWorkRela" />
							<perm name="修改" permid="updateHtcDeptWorkRela" />
							<perm name="查询" permid="queryHtcDeptWorkRela" />
						</menu_node>
						<menu_node name="科室项目定义"
							url="hrp/htc/task/projectcost/deptchargerela/htcDeptChargeRelaMainPage.do?isCheck=false">
							<perm name="添加" permid="addHtcDeptChargeRela" />
							<perm name="删除" permid="deleteHtcDeptChargeRela" />
							<perm name="修改" permid="updateHtcDeptChargeRela" />
							<perm name="查询" permid="queryHtcDeptChargeRela" />
						</menu_node>
						<menu_node name="科室职称定义"
							url="hrp/htc/task/projectcost/depttitlerela/htcDeptTitleRelaMainPage.do?isCheck=false">
							<perm name="添加" permid="addHtcDeptTitleRela" />
							<perm name="删除" permid="deleteHtcDeptTitleRela" />
							<perm name="修改" permid="updateHtcDeptTitleRela" />
							<perm name="查询" permid="queryHtcDeptTitleRela" />
						</menu_node>
						<menu_node name="科室材料定义"
							url="hrp/htc/task/projectcost/deptmaterela/htcDeptMateRelaMainPage.do?isCheck=false">
							<perm name="添加" permid="addHtcDeptMateRela" />
							<perm name="删除" permid="deleteHtcDeptMateRela" />
							<perm name="修改" permid="updateHtcDeptMateRela" />
							<perm name="查询" permid="queryHtcDeptMateRela" />
						</menu_node>
						<menu_node name="科室固定资产定义"
							url="hrp/htc/task/projectcost/deptfassetrela/htcDeptFassetRelaMainPage.do?isCheck=false">
							<perm name="添加" permid="addHtcDeptFassetRela" />
							<perm name="删除" permid="deleteHtcDeptFassetRela" />
							<perm name="修改" permid="updateHtcDeptFassetRela" />
							<perm name="查询" permid="queryHtcDeptFassetRela" />
						</menu_node>
						<menu_node name="科室无形资产定义"
							url="hrp/htc/task/projectcost/deptiassetrela/htcDeptIassetRelaMainPage.do?isCheck=false">
							<perm name="添加" permid="addHtcDeptIassetRela" />
							<perm name="删除" permid="deleteHtcDeptIassetRela" />
							<perm name="修改" permid="updateHtcDeptIassetRela" />
							<perm name="查询" permid="queryHtcDeptIassetRela" />
						</menu_node>
					</menu_node>
					<menu_node name="作业资源定义">
						<menu_node name="人员耗时比定义"
							url="hrp/htc/task/projectcost/deptworkpeopleratio/htcDeptWorkPeopleRatioMainPage.do?isCheck=false">
							<perm name="添加" permid="addHtcDeptWorkPeopleRatio" />
							<perm name="删除" permid="deleteHtcDeptWorkPeopleRatio" />
							<perm name="修改" permid="updateHtcDeptWorkPeopleRatio" />
							<perm name="查询" permid="queryHtcDeptWorkPeopleRatio" />
						</menu_node>
						<menu_node name="作业面积"
							url="hrp/htc/task/projectcost/workrear/htcWorkRearMainPage.do?isCheck=false">
							<perm name="添加" permid="addHtcWorkRear" />
							<perm name="删除" permid="deleteHtcWorkRear" />
							<perm name="修改" permid="updateHtcWorkRear" />
							<perm name="查询" permid="queryHtcWorkRear" />
						</menu_node>
					</menu_node>
					<menu_node name="项目资源定义">
						<menu_node name="活劳动资源定义">
							<menu_node name="项目作业定义"
								url="hrp/htc/task/projectcost/deptchargework/htcDeptChargeWorkDefineMainPage.do?isCheck=false">
								<perm name="保存" permid="saveHtcDeptChargeWork" />
							</menu_node>
							<menu_node name="项目作业查询"
								url="hrp/htc/task/projectcost/deptchargework/htcDeptChargeWorkMainPage.do?isCheck=false">
								<perm name="查询" permid="queryHtcDeptChargeWork" />
								<perm name="删除" permid="deleteHtcDeptChargeWork" />
							</menu_node>
							<menu_node name="活劳动资源定义"
								url="hrp/htc/task/projectcost/deptchargeworkdetail/htcDeptChargeWorkDetailDefineMainPage.do?isCheck=false">
								<perm name="保存" permid="saveHtcDeptChargeWorkDetail" />
							</menu_node>
							<menu_node name="活劳动资源查询"
								url="hrp/htc/task/projectcost/deptchargeworkdetail/htcDeptChargeWorkDetailMainPage.do?isCheck=false">
								<perm name="查询" permid="queryHtcDeptChargeWorkDetail" />
								<perm name="删除" permid="deleteHtcDeptChargeWorkDetail" />
							</menu_node>
						</menu_node>
						<menu_node name="物化劳动资源定义">
							<menu_node name="材料资源定义"
								url="hrp/htc/task/projectcost/deptchargematerela/htcDeptChargeMateRelaDefineMainPage.do?isCheck=false">
								<perm name="保存" permid="saveHtcDeptChargeMateRela" />
							</menu_node>
							<menu_node name="材料资源查询"
								url="hrp/htc/task/projectcost/deptchargematerela/htcDeptChargeMateRelaMainPage.do?isCheck=false">
								<perm name="查询" permid="queryHtcDeptChargeMateRela" />
								<perm name="删除" permid="deleteHtcDeptChargeMateRela" />
							</menu_node>
							<menu_node name="固定资产资源定义"
								url="hrp/htc/task/projectcost/deptchargefassetrela/htcDeptChargeFassetRelaDefineMainPage.do?isCheck=false">
								<perm name="保存" permid="saveHtcDeptChargeFassetRela" />
							</menu_node>
							<menu_node name="固定资产资源查询"
								url="hrp/htc/task/projectcost/deptchargefassetrela/htcDeptChargeFassetRelaMainPage.do?isCheck=false">
								<perm name="查询" permid="queryHtcDeptChargeFassetRela" />
								<perm name="删除" permid="deleteHtcDeptChargeFassetRela"/>
							</menu_node>
							<menu_node name="无形资产资源定义"
								url="hrp/htc/task/projectcost/deptchargeiassetrela/htcDeptChargeIassetRelaDefineMainPage.do?isCheck=false">
								<perm name="保存" permid="saveHtcDeptChargeIassetRela" />
							</menu_node>
							<menu_node name="无形资产资源查询"
								url="hrp/htc/task/projectcost/deptchargeiassetrela/htcDeptChargeIassetRelaMainPage.do?isCheck=false">
								<perm name="查询" permid="queryHtcDeptChargeIassetRela" />
								<perm name="删除" permid="deleteHtcDeptChargeIassetRela"/>
							</menu_node>
						</menu_node>
						<menu_node name="科室协作项目定义">
							<menu_node name="科室协作项目定义"
								url="hrp/htc/task/projectcost/chargecoop/htcChargeCoopDefineMainPage.do?isCheck=false">
								<perm name="保存" permid="saveHtcChargeCoop" />
							</menu_node>
							<menu_node name="科室协作项目查询"
								url="hrp/htc/task/projectcost/chargecoop/htcChargeCoopMainPage.do?isCheck=false">
								<perm name="查询" permid="queryHtcChargeCoop" />
								<perm name="删除" permid="deleteHtcChargeCoop" />
							</menu_node>
						</menu_node>
					</menu_node>
					<menu_node name="资源动因设置"
						url="hrp/htc/task/projectcost/rescauseset/htcResCauseSetMainPage.do?isCheck=false">
						<perm name="查询" permid="queryHtcResCauseSet" />
						<perm name="删除" permid="deleteHtcResCauseSet" />
						<perm name="批量修改" permid="updateBatchHtcResCauseSet" />
					</menu_node>
					<menu_node name="作业动因设置"
						url="hrp/htc/task/projectcost/workcauseset/htcWorkCauseSetMainPage.do?isCheck=false">
						<perm name="删除" permid="deleteHtcWorkCauseSet" />
						<perm name="查询" permid="queryHtcWorkCauseSet" />
						<perm name="批量修改" permid="updateBatchHtcWorkCauseSet" />
					</menu_node>
				</menu_node>
				<menu_node name="核算方案审核">
					<menu_node name="核算方案审核"
						url="hrp/htc/task/plan/audit/htcTaskPlanSetAuditMainPage.do?isCheck=false">
						<perm name="查询" permid="queryHtcTaskPlanSetAudit" />
						<perm name="审核" permid="auditHtcTaskPlanSet" />
						<perm name="取消审核" permid="cancelAuditHtcTaskPlanSet" />
					</menu_node>
					<menu_node name="历史方案查询"
						url="hrp/htc/task/plan/history/htcTaskPlanSetHistoryMainPage.do?isCheck=false">
						<perm name="查询" permid="queryHtcTaskPlanHistory" />
					</menu_node>
				</menu_node>
				<menu_node name="核算数据准备">
					<menu_node name="基础数据准备">
						<menu_node name="收入数据"
							url="hrp/htc/task/readydata/deptincome/htcTaskProjectCostDeptIncomeMainPage.do?isCheck=false">
							<perm name="查询" permid="queryHtcTaskProjectCostDeptIncome" />
						</menu_node>
						<menu_node name="成本数据"
							url="hrp/htc/task/readydata/deptcost/htcTaskProjectCostDeptCostMainPage.do?isCheck=false">
							<perm name="查询" permid="queryHtcTaskProjectCostDeptCost" />
						</menu_node>
						<menu_node name="活劳动数据"
							url="hrp/htc/task/readydata/deptpeople/htcTaskProjectCostDeptPeopleCostDetailMainPage.do?isCheck=false">
							<perm name="查询" permid="queryHtcTaskProjectCostDeptPeopleCostDetail" />
						</menu_node>
						<menu_node name="物化劳动-材料"
							url="hrp/htc/task/readydata/deptmate/htcTaskProjectCostDeptMaterialCostDetailMainPage.do?isCheck=false">
							<perm name="查询" permid="queryHtcTaskProjectCostDeptMaterialCostDetail" />
						</menu_node>
						<menu_node name="物化劳动-固定资产"
							url="hrp/htc/task/readydata/deptfasset/htcTaskProjectCostDeptFassetCostDetailMainPage.do?isCheck=false">
							<perm name="查询" permid="queryHtcTaskProjectCostDeptFassetCostDetail" />
						</menu_node>
						<menu_node name="物化劳动-无形资产"
							url="hrp/htc/task/readydata/deptiasset/htcTaskProjectCostDeptIassetCostDetailMainPage.do?isCheck=false">
							<perm name="查询" permid="queryHtcTaskProjectCostDeptIassetCostDetail" />
						</menu_node>
					</menu_node>
					<menu_node name="动因数据采集">
						<menu_node name="资源动因"
							url="hrp/htc/task/readydata/rescausedata/htcResCauseDataMainPage.do?isCheck=false">
							<perm name="查询" permid="queryHtcResCauseData" />
						</menu_node>
						<menu_node name="作业动因"
							url="hrp/htc/task/readydata/workcausedata/htcWorkCauseDataMainPage.do?isCheck=false">
							<perm name="查询" permid="queryHtcWorkCauseData" />
						</menu_node>
					</menu_node>
					<menu_node name="工资水平测算">
						<menu_node name="人员工时维护"
							url="hrp/htc/task/readydata/peopletime/htcPeopleTimeMainPage.do?isCheck=false">
							<perm name="查询" permid="queryHtcPeopleTime" />
							<perm name="添加" permid="addHtcPeopleTime" />
							<perm name="删除" permid="deleteHtcPeopleTime" />
							<perm name="更新" permid="updateHtcPeopleTime" />
						</menu_node>
						<menu_node name="工资水平测算"
							url="hrp/htc/task/readydata/titlecosteve/htcTitleCostEveMainPage.do?isCheck=false">
							<perm name="查询" permid="queryHtcTitleCostEve" />
							<perm name="删除" permid="deleteHtcTitleCostEve" />
						</menu_node>
					</menu_node>
				</menu_node>
				<menu_node name="项目成本核算">
					<menu_node name="科室级项目成本核算"
						url="hrp/htc/task/business/dept/htcTaskChargeCostDeptMainPage.do?isCheck=false">
						  <perm name="查询" permid="queryHtcTaskChargeCostDept" />
					</menu_node>
					<menu_node name="科室级项目成本校验">
						<menu_node name="资源动因分配校验"
							url="hrp/htc/task/business/sroucetest/htcSrouceTestMainPage.do?isCheck=false">
							<perm name="查询" permid="queryHtcSrouceTest" />
						</menu_node>
						<menu_node name="作业动因分配校验"
							url="hrp/htc/task/business/worktest/htcWorkTestMainPage.do?isCheck=false">
							<perm name="查询" permid="queryHtcWorkTest" />
						</menu_node>
					</menu_node>
					<menu_node name="院级项目成本核算" 
					     url="hrp/htc/task/business/hos/htcTaskChargeCostHosMainPage.do?isCheck=false">
						<perm name="查询" permid="queryHtcTaskChargeCostHos" />
					</menu_node>
				</menu_node>
				<menu_node name="核算结果查询">
					<menu_node name="科室级项目成本核算查询"
						url="hrp/htc/task/report/dept/htcTaskChargeCostDeptReportMainPage.do?isCheck=false">
						<perm name="查询" permid="queryHtcTaskChargeCostDeptReport" />
					</menu_node>
					<menu_node name="院级项目成本核算查询"
						url="hrp/htc/task/report/hos/htcTaskChargeCostHosReportMainPage.do?isCheck=false">
						<perm name="查询" permid="queryHtcTaskChargeCostHosReport" />
					</menu_node>
				</menu_node>
			</menu_node>
			<menu_node name="收入比法">
				<menu_node name="成本数据维护">
					<menu_node name="收入数据采集"
						url="hrp/htc/income/cost/deptincome/htcIncomeDeptIncomeMainPage.do?isCheck=false">
						<perm name="添加" permid="addHtcIncomeDeptIncome" />
						<perm name="删除" permid="deleteHtcIncomeDeptIncome" />
						<perm name="修改" permid="updateHtcIncomeDeptIncome" />
						<perm name="查询" permid="queryHtcIncomeDeptIncome" />
					</menu_node>
					<menu_node name="成本数据采集"
						url="hrp/htc/income/cost/deptcost/htcIncomeDeptCostMainPage.do?isCheck=false">
						<perm name="添加" permid="addHtcIncomeDeptCost" />
						<perm name="删除" permid="deleteHtcIncomeDeptCost" />
						<perm name="修改" permid="updateHtcIncomeDeptCost" />
						<perm name="查询" permid="queryHtcIncomeDeptCost" />
					</menu_node>
				</menu_node>
				<menu_node name="核算方案维护">
					<menu_node name="核算方案维护"
						url="hrp/htc/income/plan/set/htcIncomePlanSetMainPage.do?isCheck=false">
						<perm name="添加" permid="addHtcIncomePlanSet" />
						<perm name="删除" permid="deleteHtcIncomePlanSet" />
						<perm name="修改" permid="updateHtcIncomePlanSet" />
						<perm name="查询" permid="queryHtcIncomePlanSet" />
					</menu_node>
					<menu_node name="科室对应关系设置"
						url="hrp/htc/income/plan/deptrela/htcIncomeDeptRelaMainPage.do?isCheck=false">
						<perm name="添加" permid="addHtcIncomeDeptRela" />
						<perm name="删除" permid="deleteHtcIncomeDeptRela" />
						<perm name="修改" permid="updateHtcIncomeDeptRela" />
						<perm name="查询" permid="queryHtcIncomeDeptRela" />
					</menu_node>
				</menu_node>
				<menu_node name="核算方案审核">
					<menu_node name="核算方案审核"
						url="hrp/htc/income/plan/audit/htcIncomePlanSetAuditMainPage.do?isCheck=false">
						<perm name="查询" permid="queryHtcIncomePlanSetAudit" />
						<perm name="审核" permid="auditHtcIncomePlanSet" />
						<perm name="取消审核" permid="cancelAuditIncomeHtcPlanSet" />
					</menu_node>
					<menu_node name="历史方案查询"
						url="hrp/htc/income/plan/history/htcIncomePlanSetHistoryMainPage.do?isCheck=false">
						<perm name="查询" permid="queryHtcIncomePlanHistory" />
					</menu_node>
				</menu_node>
				<menu_node name="核算数据准备">
					<menu_node name="基础数据准备">
						<menu_node name="收入数据"
							url="hrp/htc/income/readydata/deptincome/htcIncomeProjectCostDeptIncomeMainPage.do?isCheck=false">
							<perm name="查询" permid="queryHtcIncomeProjectCostDeptIncome" />
						</menu_node>
						<menu_node name="成本数据"
							url="hrp/htc/income/readydata/deptcost/htcIncomeProjectCostDeptCostMainPage.do?isCheck=false">
							<perm name="查询" permid="queryHtcIncomeProjectCostDeptCost" />
						</menu_node>
					</menu_node>
				</menu_node>
				<menu_node name="项目成本核算">
					<menu_node name="科室级项目成本核算"
						url="hrp/htc/income/business/dept/htcIncomeChargeCostDeptMainPage.do?isCheck=false">
						<perm name="查询" permid="queryHtcIncomeChargeCostDept" />
					</menu_node>
					<menu_node name="院级项目成本核算"
						url="hrp/htc/income/business/hos/htcIncomeChargeCostHosMainPage.do?isCheck=false">
						<perm name="查询" permid="queryHtcIncomeChargeCostHos" />
					</menu_node>
				</menu_node>
				<menu_node name="核算结果查询">
					<menu_node name="科室级项目成本核算查询"
						url="hrp/htc/income/report/dept/htcIncomeChargeCostDeptReportMainPage.do?isCheck=false">
						<perm name="查询" permid="queryHtcIncomeChargeCostDeptReport" />
					</menu_node>
					<menu_node name="院级项目成本核算查询"
						url="hrp/htc/income/report/hos/htcIncomeChargeCostHosReportMainPage.do?isCheck=false">
						<perm name="查询" permid="queryHtcIncomeChargeCostHosReport" />
					</menu_node>
				</menu_node>
			</menu_node>
			<menu_node name="相对价值比率法">
				<menu_node name="成本数据维护">
					<menu_node name="收入数据采集"
						url="hrp/htc/relative/cost/deptincome/htcRelativeDeptIncomeMainPage.do?isCheck=false">
						<perm name="添加" permid="addHtcRelativeDeptIncome" />
						<perm name="删除" permid="deleteHtcRelativeDeptIncome" />
						<perm name="修改" permid="updateHtcRelativeDeptIncome" />
						<perm name="查询" permid="queryHtcRelativeDeptIncome" />
					</menu_node>
					<menu_node name="成本数据采集"
						url="hrp/htc/relative/cost/deptcost/htcRelativeDeptCostMainPage.do?isCheck=false">
						<perm name="添加" permid="addHtcRelativeDeptCost" />
						<perm name="删除" permid="deleteHtcRelativeDeptCost" />
						<perm name="修改" permid="updateHtcRelativeDeptCost" />
						<perm name="查询" permid="queryHtcRelativeDeptCost" />
					</menu_node>
				</menu_node>
				<menu_node name="核算方案维护">
					<menu_node name="核算方案维护"
						url="hrp/htc/relative/plan/set/htcRelativePlanSetMainPage.do?isCheck=false">
						<perm name="添加" permid="addHtcRelativePlanSet" />
						<perm name="删除" permid="deleteHtcRelativePlanSet" />
						<perm name="修改" permid="updateHtcRelativePlanSet" />
						<perm name="查询" permid="queryHtcRelativePlanSet" />
					</menu_node>
					<menu_node name="科室对应关系设置"
						url="hrp/htc/relative/plan/deptrela/htcRelativeDeptRelaMainPage.do?isCheck=false">
						<perm name="添加" permid="addHtcRelativeDeptRela" />
						<perm name="删除" permid="deleteHtcRelativeDeptRela" />
						<perm name="修改" permid="updateHtcRelativeDeptRela" />
						<perm name="查询" permid="queryHtcRelativeDeptRela" />
					</menu_node>
					<menu_node name="相对价值比率维护"
						url="hrp/htc/relative/plan/chargeitemvalue/htcRelativeChargeItemValueMainPage.do?isCheck=false">
						<perm name="添加" permid="addHtcRelativeChargeItemValue" />
						<perm name="删除" permid="deleteHtcRelativeChargeItemValue" />
						<perm name="修改" permid="updateHtcRelativeChargeItemValue" />
						<perm name="查询" permid="queryHtcRelativeChargeItemValue" />
					</menu_node>
				</menu_node>
				<menu_node name="核算方案审核">
					<menu_node name="核算方案审核"
						url="hrp/htc/relative/plan/audit/htcRelativePlanSetAuditMainPage.do?isCheck=false">
						<perm name="查询" permid="queryHtcRelativePlanSetAudit" />
						<perm name="审核" permid="auditHtcRelativePlanSet" />
						<perm name="取消审核" permid="cancelAuditHtcRelativePlanSet" />
					</menu_node>
					<menu_node name="历史方案查询"
						url="hrp/htc/relative/plan/history/htcRelativePlanSetHistoryMainPage.do?isCheck=false">
						<perm name="查询" permid="queryHtcRelativePlanHistory" />
					</menu_node>
				</menu_node>
				<menu_node name="核算数据准备">
					<menu_node name="基础数据准备">
						<menu_node name="收入数据"
							url="hrp/htc/relative/readydata/deptincome/htcRelativeProjectCostDeptIncomeMainPage.do?isCheck=false">
							<perm name="查询" permid="queryHtcRelativeProjectCostDeptIncome" />
						</menu_node>
						<menu_node name="成本数据"
							url="hrp/htc/relative/readydata/deptcost/htcRelativeProjectCostDeptCostMainPage.do?isCheck=false">
							<perm name="查询" permid="queryHtcRelativeProjectCostDeptCost" />
						</menu_node>
					</menu_node>
				</menu_node>
				<menu_node name="项目成本核算">
					<menu_node name="科室级项目成本核算"
						url="hrp/htc/relative/business/dept/htcRelativeChargeCostDeptMainPage.do?isCheck=false">
						<perm name="查询" permid="queryHtcRelativeChargeCostDept" />
					</menu_node>
					<menu_node name="院级项目成本核算"
						url="hrp/htc/relative/business/hos/htcRelativeChargeCostHosMainPage.do?isCheck=false">
						<perm name="查询" permid="queryHtcRelativeChargeCostHos" />
					</menu_node>
				</menu_node>
				<menu_node name="核算结果查询">
					<menu_node name="科室级项目成本核算查询"
						url="hrp/htc/relative/report/dept/htcRelativeChargeCostDeptReportMainPage.do?isCheck=false">
						<perm name="查询" permid="queryHtcRelativeChargeCostDeptReport" />
					</menu_node>
					<menu_node name="院级项目成本核算查询"
						url="hrp/htc/relative/report/hos/htcRelativeChargeCostHosReportMainPage.do?isCheck=false">
						<perm name="查询" permid="queryHtcRelativeChargeCostHosReport" />
					</menu_node>
				</menu_node>
			</menu_node>
		</menu_node>
		<menu_node code="system" name="基础设置" accordion="true">
			<menu_node name="人员信息">
				<menu_node name="人员类别"
					url="hrp/htc/task/basic/peopletypedict/htcPeopleTypeDictMainPage.do?isCheck=false">
					<perm name="添加" permid="addHtcPeopleTypeDict" />
					<perm name="删除" permid="deleteHtcPeopleTypeDict" />
					<perm name="修改" permid="updateHtcPeopleTypeDict" />
					<perm name="查询" permid="queryHtcPeopleTypeDict" />
					<perm name="同步" permid="synchroHtcPeopleTypeDict" />
				</menu_node>
				<menu_node name="人员职称字典"
					url="hrp/htc/task/basic/peopletitledict/htcPeopleTitleDictMainPage.do?isCheck=false">
					<perm name="添加" permid="addHtcPeopleTitleDict" />
					<perm name="删除" permid="deleteHtcPeopleTitleDict" />
					<perm name="修改" permid="updateHtcPeopleTitleDict" />
					<perm name="查询" permid="queryHtcPeopleTitleDict" />
					<perm name="同步" permid="synchroHtcPeopleTitleDict" />
				</menu_node>
				<menu_node name="人员资料"
					url="hrp/htc/task/basic/peopledict/htcPeopleDictMainPage.do?isCheck=false">
					<perm name="添加" permid="addHtcPeopleDict" />
					<perm name="删除" permid="deleteHtcPeopleDict" />
					<perm name="修改" permid="updateHtcPeopleDict" />
					<perm name="查询" permid="queryHtcPeopleDict" />
					<perm name="同步" permid="synchroHtcPeopleDict" />
				</menu_node>
			</menu_node>
			<menu_node name="工资信息">
				<menu_node name="工资项"
					url="hrp/htc/task/basic/wageitemdict/htcWageItemDictMainPage.do?isCheck=false">
					<perm name="添加" permid="addHtcWageItemDict" />
					<perm name="删除" permid="deleteHtcWageItemDict" />
					<perm name="修改" permid="updateHtcWageItemDict" />
					<perm name="查询" permid="queryHtcWageItemDict" />
				</menu_node>
				<menu_node name="与成本项目对应关系"
					url="hrp/htc/task/basic/wagecostrela/htcWageCostRelaMainPage.do?isCheck=false">
					<perm name="添加" permid="addHtcWageCostRela" />
					<perm name="删除" permid="deleteHtcWageCostRela" />
					<perm name="修改" permid="updateHtcWageCostRela" />
					<perm name="查询" permid="queryHtcWageCostRela" />
				</menu_node>
			</menu_node>
			<menu_node name="奖金信息">
				<menu_node name="奖金项字典"
					url="hrp/htc/task/basic/bonusitemdict/htcBonusItemDictMainPage.do?isCheck=false">
					<perm name="添加" permid="addHtcBonusItemDict" />
					<perm name="删除" permid="deleteHtcBonusItemDict" />
					<perm name="修改" permid="updateHtcBonusItemDict" />
					<perm name="查询" permid="queryHtcBonusItemDict" />
				</menu_node>
				<menu_node name="与成本项目对应关系"
					url="hrp/htc/task/basic/bonuscostrela/htcBonusCostRelaMainPage.do?isCheck=false">
					<perm name="添加" permid="addHtcBonusCostRela" />
					<perm name="删除" permid="deleteHtcBonusCostRela" />
					<perm name="修改" permid="updateHtcBonusCostRela" />
					<perm name="查询" permid="queryHtcBonusCostRela" />
				</menu_node>
			</menu_node>
			<menu_node name="固定资产">
				<menu_node name="固定资产类型"
					url="hrp/htc/task/basic/fassettypedict/htcFassetTypeDictMainPage.do?isCheck=false">
					<perm name="添加" permid="addHtcFassetTypeDict" />
					<perm name="删除" permid="deleteHtcFassetTypeDict" />
					<perm name="修改" permid="updateHtcFassetTypeDict" />
					<perm name="查询" permid="queryHtcFassetTypeDict" />
					<perm name="同步" permid="synchroHtcFassetTypeDict" />
				</menu_node>
				<menu_node name="固定资产信息"
					url="hrp/htc/task/basic/fassetdict/htcFassetDictMainPage.do?isCheck=false">
					<perm name="添加" permid="addHtcFassetDict" />
					<perm name="删除" permid="deleteHtcFassetDict" />
					<perm name="修改" permid="updateHtcFassetDict" />
					<perm name="查询" permid="queryHtcFassetDict" />
				</menu_node>
				<menu_node name="固定资产分类与成本项目的对应关系"
					url="hrp/htc/task/basic/fassetcostrela/htcFassetCostRelaMainPage.do?isCheck=false">
					<perm name="添加" permid="addHtcFassetCostRela" />
					<perm name="删除" permid="deleteHtcFassetCostRela" />
					<perm name="修改" permid="updateHtcFassetCostRela" />
					<perm name="查询" permid="queryHtcFassetCostRela" />
				</menu_node>
			</menu_node>
			<menu_node name="无形资产">
				<menu_node name="无形资产类型字典"
					url="hrp/htc/task/basic/iassettypedict/htcIassetTypeDictMainPage.do?isCheck=false">
					<perm name="添加" permid="addHtcIassetTypeDict" />
					<perm name="删除" permid="deleteHtcIassetTypeDict" />
					<perm name="修改" permid="updateHtcIassetTypeDict" />
					<perm name="查询" permid="queryHtcIassetTypeDict" />
				</menu_node>
				<menu_node name="无形资产信息字典"
					url="hrp/htc/task/basic/iassetdict/htcIassetDictMainPage.do?isCheck=false">
					<perm name="添加" permid="addHtcIassetDict" />
					<perm name="删除" permid="deleteHtcIassetDict" />
					<perm name="修改" permid="updateHtcIassetDict" />
					<perm name="查询" permid="queryHtcIassetDict" />
				</menu_node>
				<menu_node name="无形资产分类与成本项目的对应关系"
					url="hrp/htc/task/basic/iassetcostrela/htcIassetCostRelaMainPage.do?isCheck=false">
					<perm name="添加" permid="addHtcIassetCostRela" />
					<perm name="删除" permid="deleteHtcIassetCostRela" />
					<perm name="修改" permid="updateHtcIassetCostRela" />
					<perm name="查询" permid="queryHtcIassetCostRela" />
				</menu_node>
			</menu_node>
			<menu_node name="材料信息">
				<menu_node name="材料分类字典"
					url="hrp/htc/task/basic/materialtypedict/htcMaterialTypeDictMainPage.do?isCheck=false">
					<perm name="添加" permid="addHtcMaterialTypeDict" />
					<perm name="删除" permid="deleteHtcMaterialTypeDict" />
					<perm name="修改" permid="updateHtcMaterialTypeDict" />
					<perm name="查询" permid="queryHtcMaterialTypeDict" />
					<perm name="同步" permid="synchroHtcMaterialTypeDict" />
				</menu_node>
				<menu_node name="材料信息字典"
					url="hrp/htc/task/basic/materialdict/htcMaterialDictMainPage.do?isCheck=false">
					<perm name="添加" permid="addHtcMaterialDict" />
					<perm name="删除" permid="deleteHtcMaterialDict" />
					<perm name="修改" permid="updateHtcMaterialDict" />
					<perm name="查询" permid="queryHtcMaterialDict" />
					<perm name="同步" permid="synchroHtcMaterialDict" />
				</menu_node>
				<menu_node name="材料类别与成本项目的对应关系"
					url="hrp/htc/task/basic/matecostrela/htcMateCostRelaMainPage.do?isCheck=false">
					<perm name="添加" permid="addHtcMateCostRela" />
					<perm name="删除" permid="deleteHtcMateCostRela" />
					<perm name="修改" permid="updateHtcMateCostRela" />
					<perm name="查询" permid="queryHtcMateCostRela" />
				</menu_node>
			</menu_node>
			<menu_node name="其他成本字典">
				<menu_node name="资源动因维护"
					url="hrp/htc/task/basic/rescausedict/htcResCauseDictMainPage.do?isCheck=false">
					<perm name="查询" permid="queryHtcResCauseDict" />
					<perm name="添加" permid="addHtcResCauseDict" />
					<perm name="删除" permid="deleteHtcResCauseDict" />
					<perm name="修改" permid="updateHtcResCauseDict" />
				</menu_node>
				<menu_node name="作业动因维护"
					url="hrp/htc/task/basic/workcausedict/htcWorkCauseDictMainPage.do?isCheck=false">
					<perm name="添加" permid="addHtcWorkCauseDict" />
					<perm name="删除" permid="deleteHtcWorkCauseDict" />
					<perm name="修改" permid="updateHtcWorkCauseDict" />
					<perm name="查询" permid="queryHtcWorkCauseDict" />
				</menu_node>
				<menu_node name="作业分类"
					url="hrp/htc/task/basic/worktype/htcWorkTypeMainPage.do?isCheck=false">
					<perm name="添加" permid="addHtcWorkType" />
					<perm name="删除" permid="deleteHtcWorkType" />
					<perm name="修改" permid="updateHtcWorkType" />
					<perm name="查询" permid="queryHtcWorkType" />
				</menu_node>
				<menu_node name="作业字典"
					url="hrp/htc/task/basic/workdict/htcWorkDictMainPage.do?isCheck=false">
					<perm name="添加" permid="addHtcWorkDict" />
					<perm name="删除" permid="deleteHtcWorkDict" />
					<perm name="修改" permid="updateHtcWorkDict" />
					<perm name="查询" permid="queryHtcWorkDict" />
				</menu_node>
			</menu_node>
			<menu_node name="基础信息">
				<menu_node name="收入信息">
					<menu_node name="收入项目"
						url="hrp/htc/info/basic/incomeitem/htcIncomeItemDictMainPage.do?isCheck=false">
						<perm name="添加" permid="addHtcIncomeItemDict" />
						<perm name="删除" permid="deleteHtcIncomeItemDict" />
						<perm name="修改" permid="updateHtcIncomeItemDict" />
						<perm name="查询" permid="queryHtcIncomeItemDict" />
					</menu_node>
					<menu_node name="收费类别字典"
						url="hrp/htc/info/basic/chargekind/htcChargeKindDictMainPage.do?isCheck=false">
						<perm name="添加" permid="addHtcChargeKindDict" />
						<perm name="删除" permid="deleteHtcChargeKindDict" />
						<perm name="修改" permid="updateHtcChargeKindDict" />
						<perm name="查询" permid="queryHtcChargeKindDict" />
					</menu_node>
					<menu_node name="收费项目字典"
						url="hrp/htc/info/basic/chargeitem/htcChargeItemDictMainPage.do?isCheck=false">
						<perm name="添加" permid="addHtcChargeItemDict" />
						<perm name="删除" permid="deleteHtcChargeItemDict" />
						<perm name="修改" permid="updateHtcChargeItemDict" />
						<perm name="查询" permid="queryHtcChargeItemDict" />
					</menu_node>
				</menu_node>
				<menu_node name="成本信息">
					<menu_node name="成本分类"
						url="hrp/htc/info/basic/costtype/htcCostTypeDictMainPage.do?isCheck=false">
						<perm name="添加" permid="addHtcCostTypeDict" />
						<perm name="删除" permid="deleteHtcCostTypeDict" />
						<perm name="修改" permid="updateHtcCostTypeDict" />
						<perm name="查询" permid="queryHtcCostTypeDict" />
					</menu_node>
					<menu_node name="成本项目"
						url="hrp/htc/info/basic/costitem/htcCostItemDictMainPage.do?isCheck=false">
						<perm name="添加" permid="addHtcCostItemDict" />
						<perm name="删除" permid="deleteHtcCostItemDict" />
						<perm name="修改" permid="updateHtcCostItemDict" />
						<perm name="查询" permid="queryHtcCostItemDict" />
					</menu_node>
				</menu_node>
				<menu_node name="科室信息">
					<menu_node name="科室字典"
						url="hrp/htc/info/basic/dept/htcDeptDictMainPage.do?isCheck=false">
						<perm name="查询" permid="queryHtcDeptDict" />
					</menu_node>
					<menu_node name="核算科室"
						url="hrp/htc/info/basic/prodept/htcProDeptMainPage.do?isCheck=false">
						<perm name="添加" permid="addHtcProDept" />
						<perm name="删除" permid="deleteHtcProDept" />
						<perm name="修改" permid="updateHtcProDept" />
						<perm name="查询" permid="queryHtcProDept" />
					</menu_node>
				</menu_node>
			</menu_node>
		</menu_node>
		<menu_node code="xtxx" name="系统信息" accordion="true">
		</menu_node>
	</menu_node>
</root>