{
  "segments": [
    [
      {
        "description": "你可以在某些函数的搜索或者匹配的时候在比较条件中使用通配符 (?, *, ~) 。"
      }
    ],
    [
      {
        "description": "<table border=1 style='border-collapse: collapse;width:90%;'><tr><th style='width: 40%;'>通配符</th><th>Match</th></tr><tr><td>?</td><td>任意单个字符</td></tr><tr><td>*</td><td>任意字符</td></tr><tr><td>~ 跟在 ?, *, 或者 ~</td><td>?, *, 或者 ~ 的字符</td></tr></table>"
      }
    ],
    [
      {
        "description": "<b>注意:</b> 通配符只能在匹配条件为等于 (=) 的时候使用； 它不能在其它比较条件中使用 (>,<,!=,<=,>=)。"
      }
    ],
    [
      {
        "description": "通配符能够在以下函数的条件参数中使用："
      },
      {
        "list": [
          "AVERAGEIF",
          "AVERAGEIFS",
          "COUNTIF",
          "COUNTIFS",
          "SUMIF",
          "SUMIFS",
          "MATCH",
          "SEARCH",
          "VLOOKUP",
          "HLOOKUP",
          "DAVERAGE",
          "DGET",
          "DMAX",
          "DMIN",
          "DPRODUCT",
          "DSTDEV",
          "DSTDEVP",
          "DSUM",
          "DVAR",
          "DVARP"
        ]
      }
    ]
  ],
  "title": "函数使用通配符"
}
